<annotation verified="yes">
	<folder>train</folder>
	<filename>136.jpg</filename>
	<path>C:\Users\Judith989\Downloads\train\136.jpg</path>
	<source>
		<database>Unknown</database>
	</source>
	<size>
		<width>720</width>
		<height>1280</height>
		<depth>3</depth>
	</size>
	<segmented>0</segmented>
	<object>
		<name>pedestrian</name>
		<pose>Unspecified</pose>
		<truncated>0</truncated>
		<difficult>0</difficult>
		<bndbox>
			<xmin>100</xmin>
			<ymin>131</ymin>
			<xmax>272</xmax>
			<ymax>1124</ymax>
		</bndbox>
	</object>
	<object>
		<name>vehicle</name>
		<pose>Unspecified</pose>
		<truncated>0</truncated>
		<difficult>0</difficult>
		<bndbox>
			<xmin>284</xmin>
			<ymin>235</ymin>
			<xmax>668</xmax>
			<ymax>776</ymax>
		</bndbox>
	</object>
	<object>
		<name>vehicle</name>
		<pose>Unspecified</pose>
		<truncated>1</truncated>
		<difficult>0</difficult>
		<bndbox>
			<xmin>1</xmin>
			<ymin>174</ymin>
			<xmax>84</xmax>
			<ymax>401</ymax>
		</bndbox>
	</object>
</annotation>
