<annotation verified="yes">
	<folder>train</folder>
	<filename>157.jpg</filename>
	<path>C:\Users\Judith989\Downloads\train\157.jpg</path>
	<source>
		<database>Unknown</database>
	</source>
	<size>
		<width>720</width>
		<height>1280</height>
		<depth>3</depth>
	</size>
	<segmented>0</segmented>
	<object>
		<name>Traffic sign</name>
		<pose>Unspecified</pose>
		<truncated>0</truncated>
		<difficult>0</difficult>
		<bndbox>
			<xmin>42</xmin>
			<ymin>535</ymin>
			<xmax>276</xmax>
			<ymax>928</ymax>
		</bndbox>
	</object>
	<object>
		<name>vehicle</name>
		<pose>Unspecified</pose>
		<truncated>0</truncated>
		<difficult>0</difficult>
		<bndbox>
			<xmin>339</xmin>
			<ymin>271</ymin>
			<xmax>456</xmax>
			<ymax>395</ymax>
		</bndbox>
	</object>
	<object>
		<name>Traffic sign</name>
		<pose>Unspecified</pose>
		<truncated>0</truncated>
		<difficult>0</difficult>
		<bndbox>
			<xmin>460</xmin>
			<ymin>149</ymin>
			<xmax>523</xmax>
			<ymax>253</ymax>
		</bndbox>
	</object>
</annotation>
